metabaseutils/__init__.py
metabaseutils-0.0.1.dist-info/LICENSE.md
metabaseutils-0.0.1.dist-info/METADATA
metabaseutils-0.0.1.dist-info/WHEEL
metabaseutils-0.0.1.dist-info/top_level.txt
metabaseutils-0.0.1.dist-info/RECORD
