Metadata-Version: 2.1
Name: metabaseutils
Version: 0.0.1
Summary: This library can be used to export 'question' and 'dashboard' from Metabase
Home-page: https://github.com/riteshpanjwani/metabaseutils
Author: Ritesh Panjwani
Author-email: riteshpanjwani@gmail.com
License: CC BY-SA
Keywords: metabase,python
Platform: UNKNOWN
Requires-Python: >=3.6
Requires-Dist: requests
Requires-Dist: Pillow
